CHANGES.md
LICENSE.txt
MANIFEST.in
README.rst
setup.cfg
setup.py
emoji_vietnamese/__init__.py
emoji_vietnamese/core.py
emoji_vietnamese/unicode_codes.py
ilovetea.egg-info/PKG-INFO
ilovetea.egg-info/SOURCES.txt
ilovetea.egg-info/dependency_links.txt
ilovetea.egg-info/requires.txt
ilovetea.egg-info/top_level.txt
ilovetea.egg-info/zip-safe
tests/__init__.py
tests/test_core.py
tests/test_unicode_codes.py